pwbus/__init__.py
pwbus/command_line.py
pwbus/cli/command_line.py
pwbus/clients/_client.py
pwbus/clients/client.py
pwbus/clients/kafka_client.py
pwbus/clients/mongo_client.py
pwbus/clients/rabbitmq_client.py
pwbus/clients/redis_client.py
pwbus/clients/sqs_client.py
pwbus/commons/cprint.py
pwbus/commons/filesystem.py
pwbus/commons/logging.py
pwbus/configs/config.py
pwbus/connectors/_connection_pool.py
pwbus/connectors/_connector.py
pwbus/connectors/http.py
pwbus/connectors/kafka.py
pwbus/connectors/mongo.py
pwbus/connectors/rabbitmq.py
pwbus/connectors/redis.py
pwbus/connectors/sqs.py
pwbus/engines/_engine.py
pwbus/engines/_engine_thread.py
pwbus/engines/engine_dispatch.py
pwbus/engines/engine_manager.py
pwbus/engines/engine_monitor.py
pwbus/engines/engine_monitor_event.py
pwbus/engines/engine_registry.py
pwbus/engines/engine_registry_loader.py
pwbus/engines/kafka/engine.py
pwbus/engines/kafka/engine_thread.py
pwbus/engines/mongo/engine.py
pwbus/engines/mongo/engine_thread.py
pwbus/engines/rabbitmq/engine.py
pwbus/engines/rabbitmq/engine_thread.py
pwbus/engines/redis/engine.py
pwbus/engines/redis/engine_thread.py
pwbus/engines/sqs/engine.py
pwbus/engines/sqs/engine_thread.py
pwbus/flows/_flow.py
pwbus/flows/_message.py
pwbus/flows/http.py
pwbus/flows/kafka.py
pwbus/flows/mongo.py
pwbus/flows/rabbitmq.py
pwbus/flows/redis.py
pwbus/flows/sqs.py
pwbus/services/dynamic_service.py
pwbus/services/service.py
pwbus/services/service_unique_id.py
pwbus/tasks/dynamic_task.py
pwbus/tasks/task.py
pwbus/tasks/task_unique_id.py
pwbus/transformations/_transform.py
pwbus/transformations/_transform_csv.py
pwbus/transformations/_transform_json.py
pwbus/transformations/transformation.py
pwbus-0.1.64.dist-info/LICENSE.txt
pwbus-0.1.64.dist-info/METADATA
pwbus-0.1.64.dist-info/WHEEL
pwbus-0.1.64.dist-info/entry_points.txt
pwbus-0.1.64.dist-info/top_level.txt
pwbus-0.1.64.dist-info/RECORD
