Metadata-Version: 2.1
Name: pwbus
Version: 0.1.64
Summary: An integration bus capable of performing message transformation and managing task execution. Message exchange between plataforms, like HTTP, Redis, RabbitMQ, Apache Kafta, AWS SQS, MongoDB.
Home-page: https://github.com/fszostak/pwbus
Author: Fabio Szostak
Author-email: fszostak@gmail.com
License: UNKNOWN
Platform: UNKNOWN
Classifier: Development Status :: 4 - Beta
Classifier: Programming Language :: Python :: 3.7
Classifier: Programming Language :: Python :: 3.8
Classifier: License :: OSI Approved :: MIT License
Classifier: Operating System :: OS Independent
Requires-Python: >=3.7
License-File: LICENSE.txt
Requires-Dist: boto3 (==1.17.46)
Requires-Dist: botocore (==1.20.46)
Requires-Dist: certifi (>=2020.12.5)
Requires-Dist: chardet (==3.0.4)
Requires-Dist: colorama (==0.4.4)
Requires-Dist: connection-pool (==0.0.3)
Requires-Dist: cursor (==1.3.4)
Requires-Dist: docutils (==0.17)
Requires-Dist: halo (==0.0.31)
Requires-Dist: idna (==2.10)
Requires-Dist: jmespath (==0.10)
Requires-Dist: kazoo (==2.5.0)
Requires-Dist: log-symbols (==0.0.14)
Requires-Dist: pika (==1.2.0)
Requires-Dist: pykafka (==2.8.0)
Requires-Dist: pymongo (==3.11.3)
Requires-Dist: python-dateutil (==2.8.0)
Requires-Dist: python-dotenv (==0.10.3)
Requires-Dist: redis (==4.4.4)
Requires-Dist: requests (==2.25.1)
Requires-Dist: s3transfer (==0.3.6)
Requires-Dist: six (==1.15.0)
Requires-Dist: spinners (==0.0.24)
Requires-Dist: tabulate (==0.8.9)
Requires-Dist: termcolor (==1.1.0)
Requires-Dist: urllib3 (==1.26.9)
Requires-Dist: websockets (==10.3)
